{
  "title": "Kimagure Orange Road",
  "description": "La famille de Kyôsuke Kasuga vient d'emménager dans un nouvel appartement, dans un nouveau quartier, dans une nouvelle ville. Une fois de plus... Eh oui, Kyôsuke, l'aîné, partage avec ses sœurs jumelles, Manami et Kurumi, des pouvoirs paranormaux : téléportation, télékinésie, parfois rêves prémonitoires, voyages dans le temps... C'est un héritage de leur mère : toute sa famille possède des pouvoirs plus ou moins étendus.\n\nIl fait la connaissance de Madoka Ayukawa, jeune fille à la réputation sulfureuse, puis d'Hikaru Hiyama, amie d'enfance de Madoka.",
  "artist": "Izumi Matsumoto",
  "author": "Kenji Terada",
  "cover": "https://cdn.imgchest.com/files/f824290f0aa2.jpg",
  "chapters": {
    "001": {
      "title": "Un chapeau de paille rouge !",
      "volume": "",
      "last_updated": "1775854918",
      "groups": {
        "Chromatique": "/proxy/api/imgchest/chapter/dl7prnzl84o"
      }
    },
    "002": {
      "title": "Tir au panier et coup de blues !",
      "volume": "",
      "last_updated": "1775854918",
      "groups": {
        "Chromatique": "/proxy/api/imgchest/chapter/5xy2xolrn4l"
      }
    },
    "003": {
      "title": "Secret de lèvres !",
      "volume": "",
      "last_updated": "1775854918",
      "groups": {
        "Chromatique": "/proxy/api/imgchest/chapter/m9yx5ngem7q"
      }
    },
    "004": {
      "title": "Joues tristes !",
      "volume": "",
      "last_updated": "1775854918",
      "groups": {
        "Chromatique": "/proxy/api/imgchest/chapter/qe4gzqrno7j"
      }
    },
    "005": {
      "title": "Rhapsodie au bord du lac !",
      "volume": "",
      "last_updated": "1775854918",
      "groups": {
        "Chromatique": "/proxy/api/imgchest/chapter/qb4zlpkxg7j"
      }
    },
    "006": {
      "title": "Distance amoureuse !",
      "volume": "",
      "last_updated": "1775854918",
      "groups": {
        "Chromatique": "/proxy/api/imgchest/chapter/na7k2kw9k78"
      }
    },
    "007": {
      "title": "Rumeurs dangereuses !",
      "volume": "",
      "last_updated": "1775854918",
      "groups": {
        "Chromatique": "/proxy/api/imgchest/chapter/ne7br6xeky5"
      }
    },
    "008": {
      "title": "Travail secret !",
      "volume": "",
      "last_updated": "1775854918",
      "groups": {
        "Chromatique": "/proxy/api/imgchest/chapter/bp45jodwxy5"
      }
    },
    "009": {
      "title": "Premier examen !",
      "volume": "",
      "last_updated": "1775854918",
      "groups": {
        "Chromatique": "/proxy/api/imgchest/chapter/9249mkj8v7n"
      }
    },
    "010": {
      "title": "Shopping boogie !",
      "volume": "",
      "last_updated": "1775854918",
      "groups": {
        "Chromatique": "/proxy/api/imgchest/chapter/lqyewlpxxyd"
      }
    },
    "011": {
      "title": "La bague du doute !",
      "volume": "",
      "last_updated": "1775854918",
      "groups": {
        "Chromatique": "/proxy/api/imgchest/chapter/n87w8nra37x"
      }
    },
    "012": {
      "title": "Alcool blues !",
      "volume": "",
      "last_updated": "1775854918",
      "groups": {
        "Chromatique": "/proxy/api/imgchest/chapter/agyvgne3wy8"
      }
    },
    "013": {
      "title": "Sentiment trouble !",
      "volume": "",
      "last_updated": "1775854918",
      "groups": {
        "Chromatique": "/proxy/api/imgchest/chapter/9p4nqzlpw4n"
      }
    },
    "014": {
      "title": "Deux photos !",
      "volume": "",
      "last_updated": "1775854918",
      "groups": {
        "Chromatique": "/proxy/api/imgchest/chapter/a846qogegyx"
      }
    },
    "015": {
      "title": "Jealousy Rain !",
      "volume": "",
      "last_updated": "1775854918",
      "groups": {
        "Chromatique": "/proxy/api/imgchest/chapter/o24ad6kwg4l"
      }
    },
    "016": {
      "title": "Malheureux amour à sens unique !",
      "volume": "",
      "last_updated": "1775854918",
      "groups": {
        "Chromatique": "/proxy/api/imgchest/chapter/xny8r6lgp4b"
      }
    },
    "017": {
      "title": "Attention, Kurumi !",
      "volume": "",
      "last_updated": "1775854918",
      "groups": {
        "Chromatique": "/proxy/api/imgchest/chapter/9ryd32pkd7k"
      }
    },
    "018": {
      "title": "Ticket Trouble !",
      "volume": "",
      "last_updated": "1775854918",
      "groups": {
        "Chromatique": "/proxy/api/imgchest/chapter/ej7mje2dq7d"
      }
    },
    "019": {
      "title": "Panique à la plage !",
      "volume": "",
      "last_updated": "1775854918",
      "groups": {
        "Chromatique": "/proxy/api/imgchest/chapter/6eyr3ndekyp"
      }
    }
  }
}